.pre-commit-hooks.yaml
CHANGELOG.md
LICENSE
README.md
check_mkdocs/__init__.py
check_mkdocs/__main__.py
check_mkdocs/check_mkdocs.py
check_mkdocs-1.2.0.dist-info/LICENSE
check_mkdocs-1.2.0.dist-info/METADATA
check_mkdocs-1.2.0.dist-info/WHEEL
check_mkdocs-1.2.0.dist-info/entry_points.txt
check_mkdocs-1.2.0.dist-info/RECORD
