Metadata-Version: 2.1
Name: check-mkdocs
Version: 1.2.0
Summary: Simple check/command-line tool that parses, validates and loads configuration, builds the mkdocs project documentation, and serves it via a web server
Home-page: https://rodrigogonzalez.github.io/check-mkdocs/
License: MIT
Author: Rodrigo Gonzalez
Author-email: r@rodrigo-gonzalez.com
Requires-Python: >=3.8,<4.0
Classifier: License :: OSI Approved :: MIT License
Classifier: Programming Language :: Python :: 3
Classifier: Programming Language :: Python :: 3.8
Classifier: Programming Language :: Python :: 3.9
Classifier: Programming Language :: Python :: 3.10
Classifier: Programming Language :: Python :: 3.11
Requires-Dist: mkdocs (>=1.4.0,<2.0.0)
Requires-Dist: mkdocs-autolinks-plugin (>=0.7.1,<0.8.0)
Requires-Dist: mkdocs-click (>=0.8.0,<0.9.0)
Requires-Dist: mkdocs-exclude (>=1.0.2,<2.0.0)
Requires-Dist: mkdocs-exclude-search (>=0.6.5,<0.7.0)
Requires-Dist: mkdocs-jupyter (>=0.24.2,<0.25.0)
Requires-Dist: mkdocs-macros-plugin (>=1.0.4,<2.0.0)
Requires-Dist: mkdocs-material (>=9.1.6,<10.0.0)
Requires-Dist: mkdocs-monorepo-plugin (>=1.0.5,<2.0.0)
Requires-Dist: mkdocs-pdf-export-plugin (>=0.5.10,<0.6.0)
Requires-Dist: mkdocs-redirects (>=1.2.1,<2.0.0)
Requires-Dist: mkdocs-table-reader-plugin (>=2.0.1,<3.0.0)
Requires-Dist: mkdocstrings[all] (>=0.22.0,<0.23.0)
Requires-Dist: mknotebooks (>=0.8.0,<0.9.0)
Requires-Dist: pymarkdown (>=0.1.4,<0.2.0)
Requires-Dist: pyyaml (>=6.0.1,<7.0.0)
Project-URL: Repository, https://github.com/RodrigoGonzalez/check-mkdocs/
